loggingserver.py
loggingserver-1.dist-info/LICENSE
loggingserver-1.dist-info/METADATA
loggingserver-1.dist-info/WHEEL
loggingserver-1.dist-info/top_level.txt
loggingserver-1.dist-info/RECORD
